swarmauri_cert_cfssl/CfsslCertService.py
swarmauri_cert_cfssl/__init__.py
swarmauri_cert_cfssl-0.2.0.dev4.dist-info/LICENSE
swarmauri_cert_cfssl-0.2.0.dev4.dist-info/METADATA
swarmauri_cert_cfssl-0.2.0.dev4.dist-info/WHEEL
swarmauri_cert_cfssl-0.2.0.dev4.dist-info/entry_points.txt
swarmauri_cert_cfssl-0.2.0.dev4.dist-info/RECORD
