Metadata-Version: 2.3
Name: swarmauri_cert_cfssl
Version: 0.2.0.dev4
Summary: CFSSL-backed certificate service for Swarmauri
License: Apache-2.0
Author: Swarmauri
Author-email: opensource@swarmauri.com
Requires-Python: >=3.10,<3.13
Classifier: License :: OSI Approved :: Apache Software License
Classifier: Programming Language :: Python :: 3.10
Classifier: Programming Language :: Python :: 3.11
Classifier: Programming Language :: Python :: 3.12
Provides-Extra: docs
Provides-Extra: perf
Requires-Dist: cryptography
Requires-Dist: httpx
Requires-Dist: mkdocs ; extra == "docs"
Requires-Dist: pydantic (>=2.0)
Requires-Dist: pytest-benchmark (>=4.0.0) ; extra == "perf"
Requires-Dist: swarmauri_base
Requires-Dist: swarmauri_core
Requires-Dist: swarmauri_standard
